ginsapy/__init__.py
ginsapy/examples/.pylintrc
ginsapy/examples/CustomHelpFormatter.py
ginsapy/examples/GinsDataloggerReadDatFiles.dat
ginsapy/examples/__init__.py
ginsapy/examples/example_buffer_to_csv.py
ginsapy/examples/example_connect_controller.py
ginsapy/examples/example_create_buffer.py
ginsapy/examples/example_create_udbf_file_buffer.py
ginsapy/examples/example_create_udbf_file_buffer_multiple_fiiles.py
ginsapy/examples/example_csv_to_buffer.py
ginsapy/examples/example_get_buffer.py
ginsapy/examples/example_get_csv.py
ginsapy/examples/example_microphone.py
ginsapy/examples/example_read_dat_files.py
ginsapy/examples/example_websocket_read_buffer.py
ginsapy/examples/example_websocket_read_info.py
ginsapy/examples/example_websocket_read_online.py
ginsapy/examples/example_websocket_write_online.py
ginsapy/examples/assets/styles.css
ginsapy/giutility/__init__.py
ginsapy/giutility/errors.py
ginsapy/giutility/highspeedport.py
ginsapy/giutility/loader.py
ginsapy/giutility/models.py
ginsapy/giutility/postprocessbuffer.py
ginsapy/helpers/__init__.py
ginsapy/helpers/timestamp.py
ginsapy-0.4.0.dist-info/licenses/LICENSE
ginsapy-0.4.0.dist-info/METADATA
ginsapy-0.4.0.dist-info/WHEEL
ginsapy-0.4.0.dist-info/top_level.txt
ginsapy-0.4.0.dist-info/RECORD
