Metadata-Version: 2.4
Name: ginsapy
Version: 0.4.0
Summary: Gantner Instruments Highspeedport (HSP) Communication with Python
Author: Gantner Instruments
Classifier: Programming Language :: Python :: 3.10
Classifier: Programming Language :: Python :: 3.11
Classifier: Programming Language :: Python :: 3.12
Classifier: Programming Language :: Python :: 3.13
Classifier: Programming Language :: Python :: 3.14
Classifier: Operating System :: OS Independent
Requires-Python: <3.15,>=3.10
License-File: LICENSE
Requires-Dist: blinker>=1.9.0
Requires-Dist: certifi>=2025.10.5
Requires-Dist: charset-normalizer>=3.4.4
Requires-Dist: click>=8.3.0
Requires-Dist: colorama>=0.4.6
Requires-Dist: contourpy>=1.3.2
Requires-Dist: cycler>=0.12.1
Requires-Dist: dash>=3.2.0
Requires-Dist: flask>=3.1.2
Requires-Dist: fonttools>=4.60.1
Requires-Dist: idna>=3.11
Requires-Dist: importlib-metadata>=8.7.0
Requires-Dist: itsdangerous>=2.2.0
Requires-Dist: jinja2>=3.1.6
Requires-Dist: kiwisolver>=1.4.9
Requires-Dist: markupsafe>=3.0.3
Requires-Dist: matplotlib>=3.10.7
Requires-Dist: narwhals>=2.10.0
Requires-Dist: nest-asyncio>=1.6.0
Requires-Dist: numpy>=2.2.6
Requires-Dist: packaging>=25.0
Requires-Dist: pandas>=2.3.3
Requires-Dist: pillow>=12.0.0
Requires-Dist: plotly>=6.3.1
Requires-Dist: pyparsing>=3.2.5
Requires-Dist: pyqtgraph>=0.13.7
Requires-Dist: python-dateutil>=2.9.0.post0
Requires-Dist: pytz>=2025.2
Requires-Dist: requests>=2.32.5
Requires-Dist: retrying>=1.4.2
Requires-Dist: scipy>=1.15.3
Requires-Dist: six>=1.17.0
Requires-Dist: typing-extensions>=4.15.0
Requires-Dist: tzdata>=2025.2
Requires-Dist: urllib3>=2.5.0
Requires-Dist: werkzeug>=3.1.3
Requires-Dist: zipp>=3.23.0
Requires-Dist: setuptools>=80.9.0
Dynamic: license-file
